skills_agent_lib/__init__.py
skills_agent_lib/cli.py
skills_agent_lib/templates/AGENTS.md
skills_agent_lib/templates/.agents/prd.md
skills_agent_lib/templates/.agents/status.md
skills_agent_lib/templates/.agents/guides/README.md
skills_agent_lib/templates/.agents/plans/README.md
skills_agent_lib/templates/.agents/skills/agent_collaboration/SKILL.md
skills_agent_lib/templates/.agents/skills/agentic_workflow/SKILL.md
skills_agent_lib/templates/.agents/skills/agno_best_practices/SKILL.md
skills_agent_lib/templates/.agents/skills/ci_cd_best_practices/SKILL.md
skills_agent_lib/templates/.agents/skills/code_review/SKILL.md
skills_agent_lib/templates/.agents/skills/context_engineering/SKILL.md
skills_agent_lib/templates/.agents/skills/database_migrations/SKILL.md
skills_agent_lib/templates/.agents/skills/debugging/SKILL.md
skills_agent_lib/templates/.agents/skills/fastapi_best_practices/SKILL.md
skills_agent_lib/templates/.agents/skills/frontend_best_practices/SKILL.md
skills_agent_lib/templates/.agents/skills/frontend_testing_best_practices/SKILL.md
skills_agent_lib/templates/.agents/skills/git_workflow/SKILL.md
skills_agent_lib/templates/.agents/skills/how_to_create_implementation_plan/SKILL.md
skills_agent_lib/templates/.agents/skills/how_to_create_skills/SKILL.md
skills_agent_lib/templates/.agents/skills/how_to_research/SKILL.md
skills_agent_lib/templates/.agents/skills/integration_backend_frontend_best_practices/SKILL.md
skills_agent_lib/templates/.agents/skills/memory_patterns/SKILL.md
skills_agent_lib/templates/.agents/skills/prompt_engineering/SKILL.md
skills_agent_lib/templates/.agents/skills/refactoring_patterns/SKILL.md
skills_agent_lib/templates/.agents/skills/security_audit/SKILL.md
skills_agent_lib/templates/.agents/skills/software_lifecycle/SKILL.md
skills_agent_lib/templates/.agents/skills/test_driven_development/SKILL.md
skills_agent_lib/templates/.agents/skills/testing_backend_best_practices/SKILL.md
skills_agent_lib/templates/.agents/workflows/README.md
skills_agent_lib-0.3.0.dist-info/METADATA
skills_agent_lib-0.3.0.dist-info/WHEEL
skills_agent_lib-0.3.0.dist-info/entry_points.txt
skills_agent_lib-0.3.0.dist-info/licenses/LICENSE
skills_agent_lib-0.3.0.dist-info/RECORD
