Metadata-Version: 2.4
Name: skills-agent-lib
Version: 0.3.0
Summary: Portable agentic skills library with init scaffolding
Project-URL: Homepage, https://github.com/ApexIQ/skills-agent
Project-URL: Issues, https://github.com/ApexIQ/skills-agent/issues
Project-URL: Repository, https://github.com/ApexIQ/skills-agent.git
Author-email: ApexIQ <contact@apexiq.ai>
License-File: LICENSE
Keywords: agents,ai,productivity,scaffolding,skills
Classifier: Intended Audience :: Developers
Classifier: License :: OSI Approved :: MIT License
Classifier: Operating System :: OS Independent
Classifier: Programming Language :: Python :: 3
Classifier: Topic :: Software Development :: Libraries :: Python Modules
Requires-Python: >=3.9
Requires-Dist: click>=8.0
Requires-Dist: requests>=2.25.0
Requires-Dist: rich>=10.0
